CHANGELOG.rst
LICENSE
MANIFEST.in
README.rst
setup.cfg
setup.py
absoluteuri/__init__.py
absoluteuri/models.py
absoluteuri/tests.py
absoluteuri/templatetags/__init__.py
absoluteuri/templatetags/absoluteuri.py
django_absoluteuri.egg-info/PKG-INFO
django_absoluteuri.egg-info/SOURCES.txt
django_absoluteuri.egg-info/dependency_links.txt
django_absoluteuri.egg-info/requires.txt
django_absoluteuri.egg-info/top_level.txt
django_absoluteuri.egg-info/zip-safe